InstanceReduction/DataPreparation.py
InstanceReduction/Raport.py
InstanceReduction/__init__.py
InstanceReduction/Reduction/DROP1.py
InstanceReduction/Reduction/ENN.py
InstanceReduction/Reduction/ICF.py
InstanceReduction/Reduction/MSS.py
InstanceReduction/Reduction/PSC.py
InstanceReduction/Reduction/_NNGraph.py
InstanceReduction/Reduction/_Reduction.py
InstanceReduction/Reduction/__init__.py
InstanceReduction/datasets_csv/avila.csv
InstanceReduction/datasets_csv/electricity.csv
InstanceReduction/datasets_csv/fried.csv
InstanceReduction/datasets_csv/glass.csv
InstanceReduction/datasets_csv/iris.csv
InstanceReduction/datasets_csv/letter.csv
InstanceReduction/datasets_csv/liver.csv
InstanceReduction/datasets_csv/pendigits.csv
InstanceReduction/datasets_csv/satimage.csv
InstanceReduction/datasets_csv/segment.csv
InstanceReduction/datasets_csv/shuttle.csv
InstanceReduction/datasets_csv/shuttle_training.csv
InstanceReduction/datasets_csv/spambase.csv
InstanceReduction/datasets_csv/yeast.csv
tests/DROP1_test.py
tests/DataPreparation_load_test.py
tests/DataPreparation_prepar_test.py
tests/ENN_test.py
tests/ICF_test.py
tests/MSS_test.py
tests/NNGraph_test.py
tests/PCS_test.py
tests/Raport_test.py
tests/__init__.py
tests/const.py
tests/test_reduction.py
InstanceReduction-0.0.2.dist-info/LICENSE
InstanceReduction-0.0.2.dist-info/METADATA
InstanceReduction-0.0.2.dist-info/WHEEL
InstanceReduction-0.0.2.dist-info/top_level.txt
InstanceReduction-0.0.2.dist-info/RECORD
