Metadata-Version: 2.1
Name: InstanceReduction
Version: 0.0.2
Summary: Package for data reduction, especially using instance selection algorithms.
Home-page: https://github.com/paultro708/DataReduction
Author: Paulina Trofimiak
Author-email: PaulinaTrofimiak@gmail.com
License: MIT
Platform: UNKNOWN
Requires-Python: >=3.6, <3.8
Requires-Dist: numpy
Requires-Dist: pandas
Requires-Dist: matplotlib
Requires-Dist: scikit-learn
Requires-Dist: scipy
Requires-Dist: pytest
